STAPAMRTime/DataTypes.py
STAPAMRTime/GenerateReqFiles.py
STAPAMRTime/GenerateSyntheticData.py
STAPAMRTime/Optimize.py
STAPAMRTime/ParseCardData.py
STAPAMRTime/ParseVCF.py
STAPAMRTime/__init__.py
STAPAMRTime/__main__.py
STAPAMRTime-0.0.1.dist-info/LICENSE.txt
STAPAMRTime-0.0.1.dist-info/METADATA
STAPAMRTime-0.0.1.dist-info/WHEEL
STAPAMRTime-0.0.1.dist-info/entry_points.txt
STAPAMRTime-0.0.1.dist-info/top_level.txt
STAPAMRTime-0.0.1.dist-info/RECORD
