Metadata-Version: 2.1
Name: STAPAMRTime
Version: 0.0.1
Summary: Metagenomic AMR variant detection tool, part of ARMTime.
Home-page: https://github.com/imasianxd/ProjectSTAPAMRTime
Author: Baofeng Jia
Author-email: Contact@bfjia.net
License: UNKNOWN
Project-URL: Bug Tracker, https://github.com/imasianxd/ProjectSTAPAMRTime/issues
Platform: UNKNOWN
Classifier: Programming Language :: Python :: 3.7
Classifier: License :: OSI Approved :: MIT License
Classifier: Operating System :: OS Independent
Requires-Python: >=3.7
License-File: LICENSE.txt
Requires-Dist: requests (==2.27.1)
Requires-Dist: biopython (==1.72)
Requires-Dist: urllib3 (==1.26.9)
Requires-Dist: numpy (==1.21.5)
Requires-Dist: pandas (==1.3.5)
